jypkg_fileio/__init__.py
jypkg_fileio/operation.py
jypkg-0.3.dist-info/METADATA
jypkg-0.3.dist-info/WHEEL
jypkg-0.3.dist-info/top_level.txt
jypkg-0.3.dist-info/RECORD
